qgrad/__init__.py
qgrad-0.0.1.dist-info/LICENSE
qgrad-0.0.1.dist-info/METADATA
qgrad-0.0.1.dist-info/WHEEL
qgrad-0.0.1.dist-info/top_level.txt
qgrad-0.0.1.dist-info/RECORD
