Metadata-Version: 2.1
Name: qgrad
Version: 0.0.1
Summary: Autodifferentiate quantum functions 
Home-page: https://github.com/qgrad/qgrad
Author: Shahnawaz Ahmed, Asad Raza, Nathan Shammah
Author-email: shahnawaz.ahmed95@gmail.com
License: UNKNOWN
Platform: UNKNOWN
Requires-Python: >=3.6
Requires-Dist: jaxlib
Requires-Dist: numpy
